LICENSE
MANIFEST.in
README.rst
setup.cfg
setup.py
versioneer.py
tests/__init__.py
tests/test_general.py
tpRigToolkit/__init__.py
tpRigToolkit/dccs/__init__.py
tpRigToolkit/dccs/maya/__init__.py
tpRigToolkit/dccs/maya/__logging__.ini
tpRigToolkit/dccs/maya/__version__.py
tpRigToolkit/dccs/maya/_version.py
tpRigToolkit/dccs/maya/loader.py
tpRigToolkit/dccs/maya/core/__init__.py
tpRigToolkit/dccs/maya/core/control.py
tpRigToolkit/dccs/maya/core/flexiplane.py
tpRigToolkit/dccs/maya/core/joint.py
tpRigToolkit/dccs/maya/core/musclespline.py
tpRigToolkit/dccs/maya/core/rig.py
tpRigToolkit/dccs/maya/data/__init__.py
tpRigToolkit/dccs/maya/data/attributes.py
tpRigToolkit/dccs/maya/data/blendshape.py
tpRigToolkit/dccs/maya/data/controlattributes.py
tpRigToolkit/dccs/maya/data/controlcolor.py
tpRigToolkit/dccs/maya/data/controlcv.py
tpRigToolkit/dccs/maya/data/controlrotateorder.py
tpRigToolkit/dccs/maya/data/humanik.py
tpRigToolkit/dccs/maya/data/joints.py
tpRigToolkit/dccs/maya/data/ngskin.py
tpRigToolkit/dccs/maya/data/skeleton.py
tpRigToolkit/dccs/maya/data/skincluster.py
tpRigToolkit/dccs/maya/metarig/__init__.py
tpRigToolkit/dccs/maya/metarig/components/__init__.py
tpRigToolkit/dccs/maya/metarig/components/attach.py
tpRigToolkit/dccs/maya/metarig/components/buffer.py
tpRigToolkit/dccs/maya/metarig/components/fkchain.py
tpRigToolkit/dccs/maya/metarig/components/fkcurl.py
tpRigToolkit/dccs/maya/metarig/components/fkcurvechain.py
tpRigToolkit/dccs/maya/metarig/components/fksplineik.py
tpRigToolkit/dccs/maya/metarig/components/footroll.py
tpRigToolkit/dccs/maya/metarig/components/ikchain.py
tpRigToolkit/dccs/maya/metarig/components/joint.py
tpRigToolkit/dccs/maya/metarig/components/musclespline.py
tpRigToolkit/dccs/maya/metarig/components/nurbsribbon.py
tpRigToolkit/dccs/maya/metarig/components/orienttwistjoint.py
tpRigToolkit/dccs/maya/metarig/components/reversefootroll.py
tpRigToolkit/dccs/maya/metarig/components/splineikcluster.py
tpRigToolkit_dccs_maya.egg-info/PKG-INFO
tpRigToolkit_dccs_maya.egg-info/SOURCES.txt
tpRigToolkit_dccs_maya.egg-info/dependency_links.txt
tpRigToolkit_dccs_maya.egg-info/not-zip-safe
tpRigToolkit_dccs_maya.egg-info/requires.txt
tpRigToolkit_dccs_maya.egg-info/top_level.txt