Metadata-Version: 2.1
Name: tpRigToolkit-dccs-maya
Version: 0.0.2
Summary: Maya libraries for tpRigToolkit
Home-page: https://github.com/tpRigToolkit/tpRigToolkit-dccs-maya
Author: Tomas Poveda
Author-email: tpovedatd@gmail.com
License: MIT
Platform: UNKNOWN
Provides-Extra: dev
Provides-Extra: test
